.gitignore
CHANGES.txt
MANIFEST.in
README.txt
setup.py
Products/__init__.py
Products.PlacelessTranslationService.egg-info/PKG-INFO
Products.PlacelessTranslationService.egg-info/SOURCES.txt
Products.PlacelessTranslationService.egg-info/dependency_links.txt
Products.PlacelessTranslationService.egg-info/namespace_packages.txt
Products.PlacelessTranslationService.egg-info/not-zip-safe
Products.PlacelessTranslationService.egg-info/requires.txt
Products.PlacelessTranslationService.egg-info/top_level.txt
Products/PlacelessTranslationService/Domain.py
Products/PlacelessTranslationService/GettextMessageCatalog.py
Products/PlacelessTranslationService/Negotiator.py
Products/PlacelessTranslationService/PlacelessTranslationService.py
Products/PlacelessTranslationService/__init__.py
Products/PlacelessTranslationService/configure.zcml
Products/PlacelessTranslationService/interfaces.py
Products/PlacelessTranslationService/lazycatalog.py
Products/PlacelessTranslationService/load.py
Products/PlacelessTranslationService/memoize.py
Products/PlacelessTranslationService/msgfmt.py
Products/PlacelessTranslationService/overrides.zcml
Products/PlacelessTranslationService/patches.py
Products/PlacelessTranslationService/utility.py
Products/PlacelessTranslationService/utils.py
Products/PlacelessTranslationService/bin/convertToLocales.py
Products/PlacelessTranslationService/locales/PlacelessTranslationService.pot
Products/PlacelessTranslationService/locales/cs/LC_MESSAGES/PlacelessTranslationService.mo
Products/PlacelessTranslationService/locales/cs/LC_MESSAGES/PlacelessTranslationService.po
Products/PlacelessTranslationService/locales/de/LC_MESSAGES/PlacelessTranslationService.mo
Products/PlacelessTranslationService/locales/de/LC_MESSAGES/PlacelessTranslationService.po
Products/PlacelessTranslationService/locales/el/LC_MESSAGES/PlacelessTranslationService.mo
Products/PlacelessTranslationService/locales/el/LC_MESSAGES/PlacelessTranslationService.po
Products/PlacelessTranslationService/locales/pt_BR/LC_MESSAGES/PlacelessTranslationService.mo
Products/PlacelessTranslationService/locales/pt_BR/LC_MESSAGES/PlacelessTranslationService.po
Products/PlacelessTranslationService/www/GettextMessageCatalog.png
Products/PlacelessTranslationService/www/PlacelessTranslationService-32.png
Products/PlacelessTranslationService/www/PlacelessTranslationService.png
Products/PlacelessTranslationService/www/catalog_broken.pt
