Metadata-Version: 1.0
Name: Products.PlacelessTranslationService
Version: 2.0.4
Summary: PTS provides a way of internationalizing (i18n'ing) and localizing (l10n'ing) software for Zope 2.
Home-page: http://pypi.python.org/pypi/Products.PlacelessTranslationService
Author: Lalo Martins
Author-email: plone-developers@lists.sourceforge.net
License: GPL
Keywords: Zope CMF Plone i18n l10n translation gettext
Platform: UNKNOWN
Classifier: Framework :: Plone
Classifier: Framework :: Zope2
Classifier: License :: OSI Approved :: GNU General Public License (GPL)
Classifier: Programming Language :: Python
